{"cv_text": "√ìscar S√°nchez P√©rez Barcelona\nLinkedin √ìscar\ncontacto@oscarsp.dev\nAutomation Engineer ‚Äì Python & IA local\nhttps://oscarsp.dev\nResumen\nIngeniero de Automatizaci√≥n con 14 a√±os en IT y seguridad. Especializado en optimizar procesos con Python y scripting\nmultiplataforma, integrando IA local cuando aporta valor. Actualmente preparando el certificado Microsoft Azure Administrator\n(AZ-104).\nProyectos clave (todos open-source, 100% locales, sin APIs externas ni tokens)\nCVMatcher ‚Üí an√°lisis de CV con IA local, matching frente a ofertas (% de ajuste). (Python + Ollama/Mistral) [GitHub]\nPassForge ‚Üí generador de contrase√±as offline con UI/CLI (Python + Flask + secrets) [GitHub]\nIdea Tracker ‚Üí gestor de ideas con flujo de estados, CRUD completo y modo oscuro (Python + Flask + SQLite) [GitHub]\nExperiencia Laboral\nALDI Espa√±a - Automation Engineer (Automatizaci√≥n IT) Marzo 2022 ‚Äì Actualidad\nAutomatizaciones Python/PowerShell/Bash ‚Üí >50 h/mes ahorradas y menos errores manuales.\nServiceNow + utilidades internas (mailing, Software Center, Samba) con trazabilidad en Confluence.\nBase SAP/Oracle: mejoras de disponibilidad y rendimiento operativo.\nOptimizaci√≥n continua de procesos legacy: migraci√≥n de scripts manuales a soluciones automatizadas.\nLogicalis - Automation Engineer / SQL & Infra (CaixaBank/Bankia) Marzo 2021 ‚Äì Febrero 2022\nJenkins + Terraform para estandarizar despliegues y pol√≠ticas.\nDashboards en Grafana con m√©tricas SQL personalizadas, garantizando continuidad tras la fusi√≥n bancaria.\nAutomatizaci√≥n de monitorizaci√≥n y ajuste de rendimiento en SQL, mejorando eficiencia operativa.\nLuxottica - Automation Engineer (Automatizaci√≥n IT) Ene 2019 - Mar 2021\nAutomatizaciones con Python/PowerShell, logrando ~40% de eficiencia operativa.\nDesarrollo de herramientas internas en PHP/HTML5 para inventario y soporte, evitando dependencia de SaaS externos.\nSoporte y automatizaci√≥n en entornos corporativos (Steria, Amplifon, OCA, BBVA) 2011‚Äì2018\nHabilidades\nIA / LLM local: Ollama, Mistral, Llama.cpp, embeddings, RAG (FAISS/Chroma)\nAutomatizaci√≥n: Python (Flask/FastAPI, requests, pdfplumber, bs4, scapy), CLIs\nDatos: SQLite, PostgreSQL, pandas, ETL ligero\nObservabilidad y calidad: logging estructurado, m√©tricas, pytest, profiling\nSeguridad aplicada: an√°lisis de logs, CTFs, hardening\nEducaci√≥n\nCFGS Administraci√≥n de Sistemas Inform√°ticos en Red (ASIR)| STUCOM (Barcelona) 2019 ‚Äì 2025\nIdiomas\nEspa√±ol: Nativo Catalan: Nativo Ingl√©s: Mejorando nivel profesional\n", "analysis": {"skills": [{"name": "Python", "years": 14, "level": "EXPERTO", "has_work_context": true, "evidence": "Automatizaciones Python/PowerShell/Bash ‚Üí >50 h/mes ahorradas y menos errores manuales. (ALDI Espa√±a) | Desarrollo de herramientas internas en PHP/HTML5 para inventario y soporte, evitando dependencia de SaaS externos. (Luxottica)"}, {"name": "IA local", "years": 3, "level": "INTERMEDIO", "has_work_context": true, "evidence": "CVMatcher ‚Üí an√°lisis de CV con IA local, matching frente a ofertas (% de ajuste). (Python + Ollama/Mistral) | Idea Tracker ‚Üí gestor de ideas con flujo de estados, CRUD completo y modo oscuro (Python + Flask + SQLite)"}, {"name": "SQL", "years": 8, "level": "EXPERTO", "has_work_context": true, "evidence": "Base SAP/Oracle: mejoras de disponibilidad y rendimiento operativo. (ALDI Espa√±a) | Automatizaci√≥n de monitorizaci√≥n y ajuste de rendimiento en SQL, mejorando eficiencia operativa. (Logicalis)"}, {"name": "Automatizaci√≥n", "years": 14, "level": "EXPERTO", "has_work_context": true, "evidence": "Jenkins + Terraform para estandarizar despliegues y pol√≠ticas. (Logicalis) | Dashboards en Grafana con m√©tricas SQL personalizadas, garantizando continuidad tras la fusi√≥n bancaria."}, {"name": "Seguridad", "years": 14, "level": "EXPERTO", "has_work_context": true, "evidence": "An√°lisis de logs, CTFs, hardening"}, {"name": "Observabilidad y calidad", "years": 3, "level": "INTERMEDIO", "has_work_context": true, "evidence": "Logging estructurado, m√©tricas, pytest, profiling"}, {"name": "ai", "years": 3, "level": "INTERMEDIO", "has_work_context": true, "evidence": ""}, {"name": "azure", "years": 3, "level": "INTERMEDIO", "has_work_context": true, "evidence": ""}, {"name": "confluence", "years": 3, "level": "INTERMEDIO", "has_work_context": true, "evidence": ""}, {"name": "security", "years": 1, "level": "JUNIOR", "has_work_context": false, "evidence": ""}, {"name": "powershell", "years": 8, "level": "EXPERTO", "has_work_context": true, "evidence": ""}, {"name": "git", "years": 3, "level": "INTERMEDIO", "has_work_context": true, "evidence": ""}, {"name": "terraform", "years": 3, "level": "INTERMEDIO", "has_work_context": true, "evidence": ""}, {"name": "grafana", "years": 3, "level": "INTERMEDIO", "has_work_context": true, "evidence": ""}, {"name": "html", "years": 3, "level": "INTERMEDIO", "has_work_context": true, "evidence": ""}, {"name": "php", "years": 3, "level": "INTERMEDIO", "has_work_context": true, "evidence": ""}, {"name": "servicenow", "years": 3, "level": "INTERMEDIO", "has_work_context": true, "evidence": ""}, {"name": "bash", "years": 8, "level": "EXPERTO", "has_work_context": true, "evidence": ""}, {"name": "jenkins", "years": 3, "level": "INTERMEDIO", "has_work_context": true, "evidence": ""}], "especializacion_principal": "Automation Engineer", "especializacion_secundaria": "No detectada", "a√±os_experiencia_total": 14, "fortalezas_principales": ["Python", "Automatizaci√≥n", "Seguridad"], "enfoque_busqueda": {"buscar": []}, "nivel_empleabilidad": "ALTO", "salario_estimado": "N/D", "balance_skills": {"status": "bien_balanceado", "mensaje": "Excelente organizaci√≥n de skills. Todas tus competencias t√©cnicas est√°n respaldadas por experiencia profesional demostrable.", "tipo": "success"}, "informe_rrhh": {"experto": {"skills": ["Python", "SQL", "Automatizaci√≥n", "Seguridad", "powershell", "bash"], "motivo": "Has trabajado con estas tecnolog√≠as durante m√°s de 8 a√±os en posiciones como Ingeniero De Automatizaci. Experiencia s√≥lida y demostrable en entornos profesionales."}, "intermedio": {"skills": ["IA local", "Observabilidad y calidad", "ai", "azure", "confluence", "git", "terraform", "grafana", "html", "php", "servicenow", "jenkins"], "motivo": "Experiencia de 2-4 a√±os o uso ocasional en proyectos. Conocimiento funcional pero requiere supervisi√≥n en tareas complejas."}, "junior": {"skills": ["security"], "motivo": "Las mencionas en tu CV pero no hay evidencia de uso profesional significativo. RRHH podr√≠a cuestionar tu nivel real con estas tecnolog√≠as."}, "conclusion": "üîÑ Perfil balanceado: 6 skills fuertes de 19 totales. Considera potenciar algunas skills junior con ejemplos espec√≠ficos."}, "dominio": "tech", "tech_score": 1.0, "tech_evidence": ["azure", "bash", "ci", "confluence", "fastapi", "flask", "git", "github", "grafana", "jenkins", "llm", "mistral", "ollama", "pandas", "php", "postgres", "postgresql", "powershell", "python", "samba", "servicenow", "sql", "sqlite", "terraform"]}}