{"cv_text": "√ìscar S√°nchez P√©rez\nIngeniero de Automatizaci√≥n ¬∑ Python ¬∑ IA local ¬∑ Seguridad aplicada\nüìß üåê\ncontacto@oscarsp.dev https://oscarsp.dev https://github.com/oscaar90/\nOBJETIVO PROFESIONAL\nEmpec√© hace 13 a√±os arreglando sistemas que no pod√≠an fallar. Hoy sigo haciendo lo mismo, pero con otra\nmentalidad: automatizo lo que sobra, conecto piezas que no hablaban entre s√≠ y dise√±o soluciones que no\ndependan de m√≠ para seguir funcionando.\nTrabajo con Python, n8n, modelos LLM locales y herramientas de observaci√≥n como Netdata o Prometheus. No\nme interesa mantener lo que ya est√°; me interesa reescribirlo mejor.\nSi algo falla, lo arreglo. Si algo se repite, lo automatizo. Y si no hay nada, lo creo desde cero.\nEXPERIENCIA PROFESIONAL\nIngeniero de Automatizaci√≥n IT\nALDI Espa√±a - Marzo 2022 - Actualidad\nAutomatizaci√≥n de tareas repetitivas que antes hac√≠amos a mano.\nScripts en Bash, PowerShell y Python (ahorro >50 h/mes).\nColaboraci√≥n continua con comunicaci√≥n interna para automatizar campa√±as, onboardings, promociones‚Ä¶\nFlujos de mailing personalizados y mejoras operativas entre departamentos.\nToda la documentaci√≥n t√©cnica, clara y reutilizable.\nProcedimientos en Confluence: trazabilidad, soporte t√©cnico y formaci√≥n de equipos.\nCreaci√≥n y despliegue de aplicaciones internas para mejorar procesos del departamento.\nHerramientas adaptadas a necesidades reales del equipo, sin depender de soluciones externas.\nMiembro activo del equipo t√©cnico y creador de CTFs\nThe Hackers Labs (THL) 2024 ‚Äì Actualidad\nDise√±o de retos CTF con l√≥gica ofensiva, an√°lisis forense y t√©cnicas de evasi√≥n.\nEscenarios Linux con servicios reales, redes segmentadas y rutas internas.\nAutomatizaci√≥n de laboratorios para ejercicios de hacking defensivo y ofensivo.\nScripting con Bash/Python, flujos con n8n y l√≥gica adaptativa.\nIntegraci√≥n de IA local para validar flags, generar pistas o simular respuestas.\nParticipaci√≥n en el equipo central: dise√±o de infraestructura, revisi√≥n de retos y evoluci√≥n de la plataforma.\nAdministrador de Sistemas & DBA SQL ‚Äì Entornos Cr√≠ticos y Seguridad de Datos\nLogicalis (CaixaBank - Fusi√≥n con Bankia) - Mar 2021 - Feb 2022\nAdministraci√≥n avanzada de bases de datos en cl√∫steres Always On durante la fusi√≥n bancaria m√°s grande del pa√≠s.\nAlta disponibilidad, cumplimiento regulatorio y recuperaci√≥n validada.\nAutomatizaci√≥n de tareas repetitivas y despliegues mediante scripting y herramientas internas.\nBash, PowerShell y coordinaci√≥n con otros equipos t√©cnicos.\nImplementaci√≥n de un sistema de monitorizaci√≥n a medida.\nPaneles en Grafana para trazabilidad operativa y visibilidad 24/7 sobre entornos SQL cr√≠ticos.\nTrabajo transversal con seguridad y redes para validar accesos, restauraciones y auditor√≠as\nAdministrador de Sistemas ‚Äì Automatizaci√≥n de Infraestructura y Procesos IT\nLuxottica - Ene 2019 - Mar 2021\nDesarrollo de scripts y herramientas internas para eliminar tareas manuales.\nAutomatizaci√≥n de inventario, soporte y flujos operativos con PowerShell y Python.\nCoordinaci√≥n de proyectos t√©cnicos alineados con las necesidades del negocio.\nSin depender de terceros ni soluciones externas.\nSoporte de infraestructura y optimizaci√≥n continua en entornos mixtos.\nSQL Server, PHP, HTML5 y MySQL.\nEspecialista IT ‚Äì Soporte de Infraestructura, Mainframe y Bases de Datos\nSteria, Amplifon, OCA Global, BBVA ¬∑ Ene 2011 ‚Äì Dic 2018\nMantenimiento de procesos batch y programaci√≥n COBOL en entornos mainframe cr√≠ticos (BBVA),\nasegurando operativa 24/7.\nGesti√≥n de JCL (Job Control Language) para la ejecuci√≥n y automatizaci√≥n de flujos de trabajo\nheredados.\nAdministraci√≥n y optimizaci√≥n de bases de datos SQL Server con foco en integridad de datos y\nrendimiento.\nParticipaci√≥n en proyectos de migraci√≥n tecnol√≥gica e infraestructuras, actuando como enlace\nt√©cnico entre equipos y proveedores.\nFORMACI√ìN\nCFGS Administraci√≥n de Sistemas Inform√°ticos en Red (ASIR) | Finalizado 2025\nHABILIDADES T√âCNICAS\nScripting & Automatizaci√≥n\nPython ¬∑ Bash ¬∑ PowerShell ¬∑ n8n\nSistemas & Bases de Datos\nLinux ¬∑ Windows Server ¬∑ SQL Server (Always On) ¬∑ Oracle ¬∑ MySQL ¬∑ Samba ¬∑ SCCM\nObservabilidad\nGrafana, InfluxDB, Telegraf, Netdata\nInfraestructura Cl√°sica\nVMware ¬∑ Hyper-V\nHerramientas de Trabajo\nConfluence ¬∑ GitHub ¬∑ ServiceNow\nIdiomas\nEspa√±ol y Catal√°n (nativos)\nIngl√©s t√©cnico (lectura y escritura fluida)\n", "analysis": {"skills": [{"name": "ai", "years": 3, "level": "INTERMEDIO", "has_work_context": true, "evidence": ""}, {"name": "ai", "years": 3, "level": "INTERMEDIO", "has_work_context": true, "evidence": "Herramientas de Trabajo - ServiceNow"}, {"name": "git", "years": 3, "level": "INTERMEDIO", "has_work_context": true, "evidence": ""}, {"name": "git", "years": 3, "level": "INTERMEDIO", "has_work_context": true, "evidence": "Herramientas de Trabajo - ServiceNow"}, {"name": "telegraf", "years": 1, "level": "JUNIOR", "has_work_context": false, "evidence": ""}, {"name": "telegraf", "years": 1, "level": "JUNIOR", "has_work_context": false, "evidence": "Herramientas de Trabajo - ServiceNow"}, {"name": "vmware", "years": 1, "level": "JUNIOR", "has_work_context": false, "evidence": ""}, {"name": "vmware", "years": 1, "level": "JUNIOR", "has_work_context": false, "evidence": "Herramientas de Trabajo - ServiceNow"}, {"name": "servicenow", "years": 1, "level": "JUNIOR", "has_work_context": false, "evidence": ""}, {"name": "servicenow", "years": 1, "level": "JUNIOR", "has_work_context": false, "evidence": "Herramientas de Trabajo - ServiceNow"}, {"name": "windows", "years": 3, "level": "INTERMEDIO", "has_work_context": true, "evidence": ""}, {"name": "windows", "years": 3, "level": "INTERMEDIO", "has_work_context": true, "evidence": "Herramientas de Trabajo - ServiceNow"}, {"name": "security", "years": 1, "level": "JUNIOR", "has_work_context": false, "evidence": ""}, {"name": "security", "years": 1, "level": "JUNIOR", "has_work_context": false, "evidence": "Herramientas de Trabajo - ServiceNow"}, {"name": "cobol", "years": 3, "level": "INTERMEDIO", "has_work_context": true, "evidence": ""}, {"name": "cobol", "years": 3, "level": "INTERMEDIO", "has_work_context": true, "evidence": "Herramientas de Trabajo - ServiceNow"}, {"name": "sccm", "years": 3, "level": "INTERMEDIO", "has_work_context": true, "evidence": ""}, {"name": "sccm", "years": 3, "level": "INTERMEDIO", "has_work_context": true, "evidence": "Herramientas de Trabajo - ServiceNow"}, {"name": "sql", "years": 8, "level": "EXPERTO", "has_work_context": true, "evidence": ""}, {"name": "sql", "years": 8, "level": "EXPERTO", "has_work_context": true, "evidence": "Herramientas de Trabajo - ServiceNow"}, {"name": "php", "years": 3, "level": "INTERMEDIO", "has_work_context": true, "evidence": ""}, {"name": "php", "years": 3, "level": "INTERMEDIO", "has_work_context": true, "evidence": "Herramientas de Trabajo - ServiceNow"}, {"name": "influxdb", "years": 1, "level": "JUNIOR", "has_work_context": false, "evidence": ""}, {"name": "influxdb", "years": 1, "level": "JUNIOR", "has_work_context": false, "evidence": "Herramientas de Trabajo - ServiceNow"}, {"name": "html", "years": 3, "level": "INTERMEDIO", "has_work_context": true, "evidence": ""}, {"name": "html", "years": 3, "level": "INTERMEDIO", "has_work_context": true, "evidence": "Herramientas de Trabajo - ServiceNow"}, {"name": "jcl", "years": 3, "level": "INTERMEDIO", "has_work_context": true, "evidence": ""}, {"name": "jcl", "years": 3, "level": "INTERMEDIO", "has_work_context": true, "evidence": "Herramientas de Trabajo - ServiceNow"}, {"name": "powershell", "years": 8, "level": "EXPERTO", "has_work_context": true, "evidence": ""}, {"name": "powershell", "years": 8, "level": "EXPERTO", "has_work_context": true, "evidence": "Herramientas de Trabajo - ServiceNow"}, {"name": "confluence", "years": 1, "level": "JUNIOR", "has_work_context": false, "evidence": ""}, {"name": "confluence", "years": 1, "level": "JUNIOR", "has_work_context": false, "evidence": "Herramientas de Trabajo - ServiceNow"}, {"name": "bash", "years": 8, "level": "EXPERTO", "has_work_context": true, "evidence": ""}, {"name": "bash", "years": 8, "level": "EXPERTO", "has_work_context": true, "evidence": "Herramientas de Trabajo - ServiceNow"}, {"name": "python", "years": 8, "level": "EXPERTO", "has_work_context": true, "evidence": ""}, {"name": "python", "years": 8, "level": "EXPERTO", "has_work_context": true, "evidence": "Herramientas de Trabajo - ServiceNow"}, {"name": "linux", "years": 8, "level": "EXPERTO", "has_work_context": true, "evidence": ""}, {"name": "linux", "years": 8, "level": "EXPERTO", "has_work_context": true, "evidence": "Herramientas de Trabajo - ServiceNow"}, {"name": "grafana", "years": 3, "level": "INTERMEDIO", "has_work_context": true, "evidence": ""}, {"name": "grafana", "years": 3, "level": "INTERMEDIO", "has_work_context": true, "evidence": "Herramientas de Trabajo - ServiceNow"}, {"name": "n8n", "years": 3, "level": "INTERMEDIO", "has_work_context": true, "evidence": ""}, {"name": "n8n", "years": 3, "level": "INTERMEDIO", "has_work_context": true, "evidence": "Herramientas de Trabajo - ServiceNow"}, {"name": "hyper_v", "years": 1, "level": "JUNIOR", "has_work_context": false, "evidence": ""}, {"name": "hyper_v", "years": 1, "level": "JUNIOR", "has_work_context": false, "evidence": "Herramientas de Trabajo - ServiceNow"}], "especializacion_principal": "Automation Engineer", "especializacion_secundaria": "No detectada", "a√±os_experiencia_total": 13, "fortalezas_principales": ["sql", "sql", "powershell"], "enfoque_busqueda": {"buscar": []}, "nivel_empleabilidad": "ALTO", "salario_estimado": "N/D", "balance_skills": {"status": "aceptable", "mensaje": "Buen balance entre skills mencionadas y experiencia laboral. Podr√≠as considerar a√±adir m√°s contexto a algunas herramientas.", "tipo": "info"}, "informe_rrhh": {"experto": {"skills": ["sql", "sql", "powershell", "powershell", "bash", "bash", "python", "python", "linux", "linux"], "motivo": "Has trabajado con estas tecnolog√≠as durante m√°s de 8 a√±os en posiciones como Ingeniero De Automatizaci, Administrador De Sistemas. Experiencia s√≥lida y demostrable en entornos profesionales."}, "intermedio": {"skills": ["ai", "ai", "git", "git", "windows", "windows", "cobol", "cobol", "sccm", "sccm", "php", "php", "html", "html", "jcl", "jcl", "grafana", "grafana", "n8n", "n8n"], "motivo": "Experiencia de 2-4 a√±os o uso ocasional en proyectos. Conocimiento funcional pero requiere supervisi√≥n en tareas complejas."}, "junior": {"skills": ["telegraf", "telegraf", "vmware", "vmware", "servicenow", "servicenow", "security", "security", "influxdb", "influxdb", "confluence", "confluence", "hyper_v", "hyper_v"], "motivo": "Las mencionas en tu CV pero no hay evidencia de uso profesional significativo. RRHH podr√≠a cuestionar tu nivel real con estas tecnolog√≠as."}, "conclusion": "‚ö†Ô∏è Tienes 14 skills sin evidencia laboral vs 10 skills s√≥lidas. Considera eliminar skills sin experiencia real o a√±adir contexto espec√≠fico de d√≥nde las has usado."}, "dominio": "tech", "tech_score": 1.0, "tech_evidence": ["bash", "ci", "confluence", "git", "github", "go", "grafana", "hyper-v", "linux", "llm", "mysql", "netdata", "php", "powershell", "prometheus", "python", "rest", "samba", "servicenow", "sql", "vmware", "windows server"]}}