{"cv_text": "Barcelona\n√ìscar S√°nchez P√©rez\nLinkedin √ìscar\ncontacto@oscarsp.dev\nAI Tools Engineer - Python-first - Local AI & Automation https://oscarsp.dev\nResumen\nIngeniero de Automatizaci√≥n e IA con 14 a√±os en sistemas y seguridad. Desarrollo herramientas on-prem / IA local sin\ndependencias externas: extracci√≥n y normalizaci√≥n de datos, matching con LLMs y validaci√≥n determinista.\nStack: Python, Flask/FastAPI, Ollama (Mistral/Llama), embeddings, FAISS/Chroma, pdfplumber/bs4, pandas,\nSQLite/PostgreSQL, logging estructurado, pytest. Construyo soluciones s√≥lidas, medibles y documentadas.\nProyectos clave\nTodos open-source, sin APIs externas ni tokens. Ejecutan completamente en local.\nCVMatcher: An√°lisis de CV con IA local + matching [GitHub]\nExtrae skills/experiencia y genera comparativas contra ofertas; informe con % de ajuste y recomendaciones. Python,\nRequests, Ollama (Mistral), pdfplumber.\nPassForge: Generador de contrase√±as offline con UI/CLI [GitHub]\nInterfaz web + terminal, copia al portapapeles, 100% local. Python, Flask, secrets, HTML/CSS/JS.\nIdea Tracker: Gestor de ideas con control de flujo [GitHub]\nUna sola idea \"EN CURSO\" permitida, CRUD completo, modo oscuro. Python, Flask, SQLite, Jinja2.\nExperiencia Laboral\nALDI Espa√±a - Senior Systems Admin (Automatizaci√≥n IT) Marzo 2022 ‚Äì Actualidad\nAutomatizaciones Python/PowerShell/Bash ‚Üí >50 h/mes ahorradas y menos errores manuales.\nServiceNow + utilidades internas (mailing, Software Center, Samba) con trazabilidad en Confluence.\nBase SAP/Oracle: mejoras de disponibilidad y rendimiento operativo.\nOptimizaci√≥n continua de procesos legacy: migraci√≥n de scripts manuales a soluciones automatizadas.\nLogicalis (CaixaBank/Bankia) - SysAdmin & SQL DBA Marzo 2021 - Febrero 2022\nJenkins + Terraform para estandarizar despliegues y pol√≠ticas.\nGrafana con m√©tricas SQL espec√≠ficas; continuidad tras fusi√≥n bancaria.\nLuxottica - SysAdmin (Automatizaci√≥n)\nEnero 2019 - Marzo 2021\nScripts Python/PowerShell ‚Üí ~40% de eficiencia operativa.\nHerramientas internas PHP/HTML5 para inventario/soporte, sin SaaS externo.\nSteria ¬∑ Amplifon ¬∑ OCA Global ¬∑ BBVA - soporte/automatizaci√≥n 2011‚Äì2018\nbatch/JCL, SQL Server, scripting, COBOL.\nHabilidades\nIA / LLM local: Ollama, llama.cpp, Mistral/Llama, embeddings, RAG (FAISS/Chroma), evaluaci√≥n (promptfoo/Ragas)\nAutomatizaci√≥n Python: Flask/FastAPI, requests/async, pdfplumber/bs4/lxml, scapy/tshark, CLIs\nDatos: SQLite/PostgreSQL, pandas, ETL ligero\nObservabilidad y calidad: logging estructurado, m√©tricas, pytest, profiling\nSeguridad aplicada: an√°lisis de logs, dise√±o de retos CTF, hardening b√°sico\nEducaci√≥n\nCFGS Administraci√≥n de Sistemas Inform√°ticos en Red (ASIR)| STUCOM (Barcelona) 2019 ‚Äì 2025 FINALIZADO\nIdiomas\nEspa√±ol: Nativo Catalan: Nativo Ingl√©s: Conversaci√≥n\n", "analysis": {"skills": [{"name": "ai", "years": 3, "level": "INTERMEDIO", "has_work_context": true, "evidence": ""}, {"name": "ai", "years": 3, "level": "INTERMEDIO", "has_work_context": true, "evidence": "Basic hardening, CTF challenge design, log analysis."}, {"name": "php", "years": 3, "level": "INTERMEDIO", "has_work_context": true, "evidence": ""}, {"name": "php", "years": 3, "level": "INTERMEDIO", "has_work_context": true, "evidence": "Basic hardening, CTF challenge design, log analysis."}, {"name": "git", "years": 3, "level": "INTERMEDIO", "has_work_context": true, "evidence": ""}, {"name": "git", "years": 3, "level": "INTERMEDIO", "has_work_context": true, "evidence": "Basic hardening, CTF challenge design, log analysis."}, {"name": "grafana", "years": 3, "level": "INTERMEDIO", "has_work_context": true, "evidence": ""}, {"name": "grafana", "years": 3, "level": "INTERMEDIO", "has_work_context": true, "evidence": "Basic hardening, CTF challenge design, log analysis."}, {"name": "servicenow", "years": 3, "level": "INTERMEDIO", "has_work_context": true, "evidence": ""}, {"name": "servicenow", "years": 3, "level": "INTERMEDIO", "has_work_context": true, "evidence": "Basic hardening, CTF challenge design, log analysis."}, {"name": "jenkins", "years": 3, "level": "INTERMEDIO", "has_work_context": true, "evidence": ""}, {"name": "jenkins", "years": 3, "level": "INTERMEDIO", "has_work_context": true, "evidence": "Basic hardening, CTF challenge design, log analysis."}, {"name": "jcl", "years": 3, "level": "INTERMEDIO", "has_work_context": true, "evidence": ""}, {"name": "jcl", "years": 3, "level": "INTERMEDIO", "has_work_context": true, "evidence": "Basic hardening, CTF challenge design, log analysis."}, {"name": "confluence", "years": 3, "level": "INTERMEDIO", "has_work_context": true, "evidence": ""}, {"name": "confluence", "years": 3, "level": "INTERMEDIO", "has_work_context": true, "evidence": "Basic hardening, CTF challenge design, log analysis."}, {"name": "cobol", "years": 3, "level": "INTERMEDIO", "has_work_context": true, "evidence": ""}, {"name": "cobol", "years": 3, "level": "INTERMEDIO", "has_work_context": true, "evidence": "Basic hardening, CTF challenge design, log analysis."}, {"name": "css", "years": 1, "level": "JUNIOR", "has_work_context": false, "evidence": ""}, {"name": "css", "years": 1, "level": "JUNIOR", "has_work_context": false, "evidence": "Basic hardening, CTF challenge design, log analysis."}, {"name": "sql", "years": 8, "level": "EXPERTO", "has_work_context": true, "evidence": ""}, {"name": "sql", "years": 8, "level": "EXPERTO", "has_work_context": true, "evidence": "Basic hardening, CTF challenge design, log analysis."}, {"name": "python", "years": 8, "level": "EXPERTO", "has_work_context": true, "evidence": ""}, {"name": "python", "years": 8, "level": "EXPERTO", "has_work_context": true, "evidence": "Basic hardening, CTF challenge design, log analysis."}, {"name": "javascript", "years": 1, "level": "JUNIOR", "has_work_context": false, "evidence": ""}, {"name": "javascript", "years": 1, "level": "JUNIOR", "has_work_context": false, "evidence": "Basic hardening, CTF challenge design, log analysis."}, {"name": "security", "years": 1, "level": "JUNIOR", "has_work_context": false, "evidence": ""}, {"name": "security", "years": 1, "level": "JUNIOR", "has_work_context": false, "evidence": "Basic hardening, CTF challenge design, log analysis."}, {"name": "bash", "years": 8, "level": "EXPERTO", "has_work_context": true, "evidence": ""}, {"name": "bash", "years": 8, "level": "EXPERTO", "has_work_context": true, "evidence": "Basic hardening, CTF challenge design, log analysis."}, {"name": "terraform", "years": 3, "level": "INTERMEDIO", "has_work_context": true, "evidence": ""}, {"name": "terraform", "years": 3, "level": "INTERMEDIO", "has_work_context": true, "evidence": "Basic hardening, CTF challenge design, log analysis."}, {"name": "html", "years": 3, "level": "INTERMEDIO", "has_work_context": true, "evidence": ""}, {"name": "html", "years": 3, "level": "INTERMEDIO", "has_work_context": true, "evidence": "Basic hardening, CTF challenge design, log analysis."}, {"name": "powershell", "years": 8, "level": "EXPERTO", "has_work_context": true, "evidence": ""}, {"name": "powershell", "years": 8, "level": "EXPERTO", "has_work_context": true, "evidence": "Basic hardening, CTF challenge design, log analysis."}], "especializacion_principal": "AI Tools Engineer", "especializacion_secundaria": "No detectada", "a√±os_experiencia_total": 14, "fortalezas_principales": ["sql", "sql", "python"], "enfoque_busqueda": {"buscar": []}, "nivel_empleabilidad": "ALTO", "salario_estimado": "N/D", "balance_skills": {"status": "bien_balanceado", "mensaje": "Excelente organizaci√≥n de skills. Todas tus competencias t√©cnicas est√°n respaldadas por experiencia profesional demostrable.", "tipo": "success"}, "informe_rrhh": {"experto": {"skills": ["sql", "sql", "python", "python", "bash", "bash", "powershell", "powershell"], "motivo": "Has trabajado con estas tecnolog√≠as durante m√°s de 8 a√±os en posiciones como Ingeniero De Automatizaci. Experiencia s√≥lida y demostrable en entornos profesionales."}, "intermedio": {"skills": ["ai", "ai", "php", "php", "git", "git", "grafana", "grafana", "servicenow", "servicenow", "jenkins", "jenkins", "jcl", "jcl", "confluence", "confluence", "cobol", "cobol", "terraform", "terraform", "html", "html"], "motivo": "Experiencia de 2-4 a√±os o uso ocasional en proyectos. Conocimiento funcional pero requiere supervisi√≥n en tareas complejas."}, "junior": {"skills": ["css", "css", "javascript", "javascript", "security", "security"], "motivo": "Las mencionas en tu CV pero no hay evidencia de uso profesional significativo. RRHH podr√≠a cuestionar tu nivel real con estas tecnolog√≠as."}, "conclusion": "üîÑ Perfil balanceado: 8 skills fuertes de 36 totales. Considera potenciar algunas skills junior con ejemplos espec√≠ficos."}, "dominio": "tech", "tech_score": 1.0, "tech_evidence": ["bash", "ci", "confluence", "fastapi", "flask", "git", "github", "grafana", "jenkins", "llm", "mistral", "ollama", "pandas", "php", "postgres", "postgresql", "powershell", "python", "samba", "servicenow", "sql", "sqlite", "terraform"]}}