{"cv_text": "Barcelona\nÓscar Sánchez Pérez\nLinkedin Óscar\ncontacto@oscarsp.dev\nAI Tools Engineer - Python-first - Local AI & Automation https://oscarsp.dev\nResumen\nIngeniero de Automatización e IA con 14 años en sistemas y seguridad. Desarrollo herramientas on-prem / IA local sin\ndependencias externas: extracción y normalización de datos, matching con LLMs y validación determinista.\nStack: Python, Flask/FastAPI, Ollama (Mistral/Llama), embeddings, FAISS/Chroma, pdfplumber/bs4, pandas,\nSQLite/PostgreSQL, logging estructurado, pytest. Construyo soluciones sólidas, medibles y documentadas.\nProyectos clave\nTodos open-source, sin APIs externas ni tokens. Ejecutan completamente en local.\nCVMatcher: Análisis de CV con IA local + matching [GitHub]\nExtrae skills/experiencia y genera comparativas contra ofertas; informe con % de ajuste y recomendaciones. Python,\nRequests, Ollama (Mistral), pdfplumber.\nPassForge: Generador de contraseñas offline con UI/CLI [GitHub]\nInterfaz web + terminal, copia al portapapeles, 100% local. Python, Flask, secrets, HTML/CSS/JS.\nIdea Tracker: Gestor de ideas con control de flujo [GitHub]\nUna sola idea \"EN CURSO\" permitida, CRUD completo, modo oscuro. Python, Flask, SQLite, Jinja2.\nExperiencia Laboral\nALDI España - Senior Systems Admin (Automatización IT) Marzo 2022 – Actualidad\nAutomatizaciones Python/PowerShell/Bash → >50 h/mes ahorradas y menos errores manuales.\nServiceNow + utilidades internas (mailing, Software Center, Samba) con trazabilidad en Confluence.\nBase SAP/Oracle: mejoras de disponibilidad y rendimiento operativo.\nOptimización continua de procesos legacy: migración de scripts manuales a soluciones automatizadas.\nLogicalis (CaixaBank/Bankia) - SysAdmin & SQL DBA Marzo 2021 - Febrero 2022\nJenkins + Terraform para estandarizar despliegues y políticas.\nGrafana con métricas SQL específicas; continuidad tras fusión bancaria.\nLuxottica - SysAdmin (Automatización)\nEnero 2019 - Marzo 2021\nScripts Python/PowerShell → ~40% de eficiencia operativa.\nHerramientas internas PHP/HTML5 para inventario/soporte, sin SaaS externo.\nSteria · Amplifon · OCA Global · BBVA - soporte/automatización 2011–2018\nbatch/JCL, SQL Server, scripting, COBOL.\nHabilidades\nIA / LLM local: Ollama, llama.cpp, Mistral/Llama, embeddings, RAG (FAISS/Chroma), evaluación (promptfoo/Ragas)\nAutomatización Python: Flask/FastAPI, requests/async, pdfplumber/bs4/lxml, scapy/tshark, CLIs\nDatos: SQLite/PostgreSQL, pandas, ETL ligero\nObservabilidad y calidad: logging estructurado, métricas, pytest, profiling\nSeguridad aplicada: análisis de logs, diseño de retos CTF, hardening básico\nEducación\nCFGS Administración de Sistemas Informáticos en Red (ASIR)| STUCOM (Barcelona) 2019 – 2025 FINALIZADO\nIdiomas\nEspañol: Nativo Catalan: Nativo Inglés: Conversación\n", "analysis": {"skills": [{"name": "Python", "years": 8, "level": "EXPERTO", "has_work_context": true, "evidence": "Stack: Python, Flask/FastAPI..."}, {"name": "Automation", "years": 8, "level": "EXPERTO", "has_work_context": true, "evidence": "Automatizaciones Python/PowerShell/Bash → >50 h/mes ahorradas y menos errores manuales."}, {"name": "Flask", "years": 8, "level": "EXPERTO", "has_work_context": true, "evidence": "Stack: Python, Flask/FastAPI..."}, {"name": "FastAPI", "years": 3, "level": "INTERMEDIO", "has_work_context": true, "evidence": "Stack: Python, Flask/FastAPI..."}, {"name": "PowerShell", "years": 8, "level": "EXPERTO", "has_work_context": true, "evidence": "Automatizaciones Python/PowerShell/Bash → >50 h/mes ahorradas y menos errores manuales."}, {"name": "Bash", "years": 8, "level": "EXPERTO", "has_work_context": true, "evidence": "Automatizaciones Python/PowerShell/Bash → >50 h/mes ahorradas y menos errores manuales."}, {"name": "ServiceNow", "years": 3, "level": "INTERMEDIO", "has_work_context": true, "evidence": "ServiceNow + utilidades internas (mailing, Software Center, Samba) con trazabilidad en Confluence."}, {"name": "Terraform", "years": 3, "level": "INTERMEDIO", "has_work_context": true, "evidence": "Jenkins + Terraform para estandarizar despliegues y políticas."}, {"name": "Grafana", "years": 3, "level": "INTERMEDIO", "has_work_context": true, "evidence": "Grafana con métricas SQL específicas; continuidad tras fusión bancaria."}, {"name": "SAP", "years": 3, "level": "INTERMEDIO", "has_work_context": true, "evidence": "Base SAP/Oracle: mejoras de disponibilidad y rendimiento operativo."}, {"name": "Oracle", "years": 3, "level": "INTERMEDIO", "has_work_context": true, "evidence": "Base SAP/Oracle: mejoras de disponibilidad y rendimiento operativo."}, {"name": "SQL Server", "years": 3, "level": "INTERMEDIO", "has_work_context": true, "evidence": "Steria · Amplifon · OCA Global · BBVA - soporte/automatización 2011–2018"}, {"name": "COBOL", "years": 3, "level": "INTERMEDIO", "has_work_context": true, "evidence": "Steria · Amplifon · OCA Global · BBVA - soporte/automatización 2011–2018"}, {"name": "batch", "years": 3, "level": "INTERMEDIO", "has_work_context": true, "evidence": "Steria · Amplifon · OCA Global · BBVA - soporte/automatización 2011–2018"}, {"name": "JCL", "years": 3, "level": "INTERMEDIO", "has_work_context": true, "evidence": "Steria · Amplifon · OCA Global · BBVA - soporte/automatización 2011–2018"}, {"name": "scripting", "years": 3, "level": "INTERMEDIO", "has_work_context": true, "evidence": "Steria · Amplifon · OCA Global · BBVA - soporte/automatización 2011–2018"}, {"name": "Ollama", "years": 3, "level": "INTERMEDIO", "has_work_context": true, "evidence": "IA / LLM local: Ollama, llama.cpp, Mistral/Llama, embeddings, RAG (FAISS/Chroma), evaluación (promptfoo/Ragas)"}, {"name": "llama.cpp", "years": 3, "level": "INTERMEDIO", "has_work_context": true, "evidence": "IA / LLM local: Ollama, llama.cpp, Mistral/Llama, embeddings, RAG (FAISS/Chroma), evaluación (promptfoo/Ragas)"}, {"name": "Mistral", "years": 3, "level": "INTERMEDIO", "has_work_context": true, "evidence": "IA / LLM local: Ollama, llama.cpp, Mistral/Llama, embeddings, RAG (FAISS/Chroma), evaluación (promptfoo/Ragas)"}, {"name": "embeddings", "years": 3, "level": "INTERMEDIO", "has_work_context": true, "evidence": "IA / LLM local: Ollama, llama.cpp, Mistral/Llama, embeddings, RAG (FAISS/Chroma), evaluación (promptfoo/Ragas)"}, {"name": "RAG", "years": 3, "level": "INTERMEDIO", "has_work_context": true, "evidence": "IA / LLM local: Ollama, llama.cpp, Mistral/Llama, embeddings, RAG (FAISS/Chroma), evaluación (promptfoo/Ragas)"}, {"name": "FAISS", "years": 3, "level": "INTERMEDIO", "has_work_context": true, "evidence": "IA / LLM local: Ollama, llama.cpp, Mistral/Llama, embeddings, RAG (FAISS/Chroma), evaluación (promptfoo/Ragas)"}, {"name": "Chroma", "years": 3, "level": "INTERMEDIO", "has_work_context": true, "evidence": "IA / LLM local: Ollama, llama.cpp, Mistral/Llama, embeddings, RAG (FAISS/Chroma), evaluación (promptfoo/Ragas)"}, {"name": "promptfoo", "years": 3, "level": "INTERMEDIO", "has_work_context": true, "evidence": "IA / LLM local: Ollama, llama.cpp, Mistral/Llama, embeddings, RAG (FAISS/Chroma), evaluación (promptfoo/Ragas)"}, {"name": "Ragas", "years": 3, "level": "INTERMEDIO", "has_work_context": true, "evidence": "IA / LLM local: Ollama, llama.cpp, Mistral/Llama, embeddings, RAG (FAISS/Chroma), evaluación (promptfoo/Ragas)"}, {"name": "requests", "years": 3, "level": "INTERMEDIO", "has_work_context": true, "evidence": "Automatización Python: Flask/FastAPI, requests/async,"}, {"name": "async", "years": 3, "level": "INTERMEDIO", "has_work_context": true, "evidence": "Automatización Python: Flask/FastAPI, requests/async,"}, {"name": "pdfplumber", "years": 3, "level": "INTERMEDIO", "has_work_context": true, "evidence": "Automatización Python: Flask/FastAPI, requests/async, pdfplumber/bs4/lxml,"}, {"name": "bs4", "years": 3, "level": "INTERMEDIO", "has_work_context": true, "evidence": "Automatización Python: Flask/FastAPI, requests/async, pdfplumber/bs4/lxml,"}, {"name": "lxml", "years": 3, "level": "INTERMEDIO", "has_work_context": true, "evidence": "Automatización Python: Flask/FastAPI, requests/async, pdfplumber/bs4/lxml,"}, {"name": "scapy", "years": 3, "level": "INTERMEDIO", "has_work_context": true, "evidence": "Automatización Python: Flask/FastAPI, requests/async, pdfplumber/bs4/lxml, scapy/tshark,"}, {"name": "tshark", "years": 3, "level": "INTERMEDIO", "has_work_context": true, "evidence": "Automatización Python: Flask/FastAPI, requests/async, pdfplumber/bs4/lxml, scapy/tshark,"}, {"name": "SQLite", "years": 3, "level": "INTERMEDIO", "has_work_context": true, "evidence": "Stack: Python, Flask/FastAPI, Ollama (Mistral/Llama), embeddings, FAISS/Chroma, pdfplumber/bs4, pandas,"}, {"name": "PostgreSQL", "years": 8, "level": "EXPERTO", "has_work_context": true, "evidence": "Stack: Python, Flask/FastAPI, Ollama (Mistral/Llama), embeddings, FAISS/Chroma, pdfplumber/bs4, pandas,"}, {"name": "pandas", "years": 3, "level": "INTERMEDIO", "has_work_context": true, "evidence": "Stack: Python, Flask/FastAPI, Ollama (Mistral/Llama), embeddings, FAISS/Chroma, pdfplumber/bs4, pandas,"}, {"name": "ETL", "years": 3, "level": "INTERMEDIO", "has_work_context": true, "evidence": "Datos: SQLite/PostgreSQL, pandas, ETL ligero"}, {"name": "logging estructurado", "years": 3, "level": "INTERMEDIO", "has_work_context": true, "evidence": "Observabilidad y calidad: logging estructurado,"}, {"name": "métricas", "years": 3, "level": "INTERMEDIO", "has_work_context": true, "evidence": "Observabilidad y calidad: logging estructurado, métricas,"}, {"name": "pytest", "years": 3, "level": "INTERMEDIO", "has_work_context": true, "evidence": "Observabilidad y calidad: logging estructurado, métricas, pytest,"}, {"name": "profiling", "years": 3, "level": "INTERMEDIO", "has_work_context": true, "evidence": "Observabilidad y calidad: logging estructurado, métricas, pytest, profiling"}, {"name": "secrets", "years": 1, "level": "JUNIOR", "has_work_context": false, "evidence": "PassForge: Generador de contraseñas offline con UI/CLI [GitHub] Interfaz web + terminal,"}, {"name": "HTML", "years": 3, "level": "INTERMEDIO", "has_work_context": true, "evidence": "PassForge: Generador de contraseñas offline con UI/CLI [GitHub] Interfaz web + terminal, copia al portapapeles,"}, {"name": "CSS", "years": 1, "level": "JUNIOR", "has_work_context": false, "evidence": "PassForge: Generador de contraseñas offline con UI/CLI [GitHub] Interfaz web + terminal, copia al portapapeles,"}, {"name": "JS", "years": 1, "level": "JUNIOR", "has_work_context": false, "evidence": "PassForge: Generador de contraseñas offline con UI/CLI [GitHub] Interfaz web + terminal, copia al portapapeles,"}, {"name": "Análisis de logs", "years": 3, "level": "INTERMEDIO", "has_work_context": true, "evidence": "Seguridad aplicada: análisis de logs,"}, {"name": "diseño de retos CTF", "years": 3, "level": "INTERMEDIO", "has_work_context": true, "evidence": "Seguridad aplicada: diseño de retos CTF,"}, {"name": "hardening básico", "years": 3, "level": "INTERMEDIO", "has_work_context": true, "evidence": "Seguridad aplicada: análisis de logs, diseño de retos CTF, hardening básico"}], "especializacion_principal": "AI Tools Engineer", "especializacion_secundaria": "No detectada", "años_experiencia_total": 14, "fortalezas_principales": ["Python", "Automation", "Flask"], "enfoque_busqueda": {"buscar": ["DevOps Engineer", "Automation Engineer", "SRE", "Infrastructure Engineer", "Platform Engineer"], "ranking": [{"role": "Automation Engineer", "fit_percent": 95}, {"role": "DevOps Engineer", "fit_percent": 92}, {"role": "SRE", "fit_percent": 88}, {"role": "Infrastructure Engineer", "fit_percent": 70}, {"role": "Platform Engineer", "fit_percent": 65}]}, "nivel_empleabilidad": "ALTO", "salario_estimado": "N/D", "balance_skills": {"status": "bien_balanceado", "mensaje": "Excelente organización de skills. Todas tus competencias técnicas están respaldadas por experiencia profesional demostrable.", "tipo": "success"}, "informe_rrhh": {"experto": {"skills": ["Python", "Automation", "Flask", "PowerShell", "Bash", "PostgreSQL"], "motivo": "Has trabajado con estas tecnologías durante más de 8 años en posiciones como Ingeniero De Automatizaci. Experiencia sólida y demostrable en entornos profesionales."}, "intermedio": {"skills": ["FastAPI", "ServiceNow", "Terraform", "Grafana", "SAP", "Oracle", "SQL Server", "COBOL", "batch", "JCL", "scripting", "Ollama", "llama.cpp", "Mistral", "embeddings", "RAG", "FAISS", "Chroma", "promptfoo", "Ragas", "requests", "async", "pdfplumber", "bs4", "lxml", "scapy", "tshark", "SQLite", "pandas", "ETL", "logging estructurado", "métricas", "pytest", "profiling", "HTML", "Análisis de logs", "diseño de retos CTF", "hardening básico"], "motivo": "Experiencia de 2-4 años o uso ocasional en proyectos. Conocimiento funcional pero requiere supervisión en tareas complejas."}, "junior": {"skills": ["secrets", "CSS", "JS"], "motivo": "Las mencionas en tu CV pero no hay evidencia de uso profesional significativo. RRHH podría cuestionar tu nivel real con estas tecnologías."}, "conclusion": "🔄 Perfil balanceado: 6 skills fuertes de 47 totales. Considera potenciar algunas skills junior con ejemplos específicos."}, "dominio": "tech", "tech_score": 1.0, "tech_evidence": ["bash", "ci", "confluence", "fastapi", "flask", "git", "github", "grafana", "jenkins", "llm", "mistral", "ollama", "pandas", "php", "postgres", "postgresql", "powershell", "python", "samba", "servicenow", "sql", "sqlite", "terraform"]}}